{
  "name": "Smart Task Planner - Wireframes",
  "description": "Complete wireframe structure for Smart Task Planner app",
  "version": "1.0.0",
  "screens": [
    {
      "id": "screen_dashboard",
      "name": "Dashboard - Main View",
      "width": 1440,
      "height": 900,
      "description": "Main dashboard with calendar, tasks, and empty state",
      "sections": [
        {
          "id": "header",
          "name": "Header",
          "type": "component",
          "position": { "x": 0, "y": 0, "width": 1440, "height": 64 },
          "description": "Top navigation bar",
          "children": [
            {
              "id": "logo",
              "name": "Logo & Title",
              "type": "group",
              "position": { "x": 16, "y": 8, "width": 200, "height": 48 },
              "content": "📅 Task Planner - Smart Planner"
            },
            {
              "id": "command_btn",
              "name": "Command Palette Button",
              "type": "button",
              "position": { "x": 600, "y": 12, "width": 120, "height": 40 },
              "content": "🔍 Command"
            },
            {
              "id": "language_toggle",
              "name": "Language Toggle (EN/ID)",
              "type": "radio_group",
              "position": { "x": 850, "y": 12, "width": 100, "height": 40 },
              "options": ["🇬🇧 EN", "🇮🇩 ID"]
            },
            {
              "id": "theme_toggle",
              "name": "Theme Toggle",
              "type": "button",
              "position": { "x": 970, "y": 12, "width": 40, "height": 40 },
              "content": "🌙/☀️"
            },
            {
              "id": "menu",
              "name": "Menu",
              "type": "button",
              "position": { "x": 1400, "y": 12, "width": 40, "height": 40 },
              "content": "☰"
            }
          ]
        },
        {
          "id": "calendar_section",
          "name": "Calendar Timeline Section",
          "type": "component",
          "position": { "x": 0, "y": 64, "width": 1440, "height": 280 },
          "description": "Month calendar view with today quick view",
          "children": [
            {
              "id": "today_card",
              "name": "Today Quick View",
              "type": "card",
              "position": { "x": 16, "y": 16, "width": 1408, "height": 80 },
              "bgColor": "linear-gradient(135deg, #EFF6FF, #CFFAFE)",
              "content": "📅 Today: Monday, April 7, 2026 | Tasks: 5"
            },
            {
              "id": "month_nav",
              "name": "Month Navigation",
              "type": "group",
              "position": { "x": 16, "y": 110, "width": 1408, "height": 40 },
              "children": [
                {
                  "id": "prev_btn",
                  "name": "Previous Month",
                  "type": "button",
                  "position": { "x": 0, "y": 0, "width": 40, "height": 40 }
                },
                {
                  "id": "month_title",
                  "name": "April 2026",
                  "type": "text",
                  "position": { "x": 100, "y": 8, "width": 200, "height": 24 }
                },
                {
                  "id": "today_btn",
                  "name": "Today Button",
                  "type": "button",
                  "position": { "x": 450, "y": 0, "width": 60, "height": 40 }
                },
                {
                  "id": "next_btn",
                  "name": "Next Month",
                  "type": "button",
                  "position": { "x": 1368, "y": 0, "width": 40, "height": 40 }
                }
              ]
            },
            {
              "id": "calendar_grid",
              "name": "Calendar Grid",
              "type": "grid",
              "position": { "x": 16, "y": 160, "width": 1408, "height": 110 },
              "columns": 7,
              "description": "7x4 grid showing all days of month",
              "cellSpacing": 8
            }
          ]
        },
        {
          "id": "tasks_section",
          "name": "Tasks Display Section",
          "type": "component",
          "position": { "x": 0, "y": 344, "width": 1440, "height": 556 },
          "description": "Main task list or empty state",
          "children": [
            {
              "id": "task_view_modes",
              "name": "View Mode Selector",
              "type": "button_group",
              "position": { "x": 16, "y": 16, "width": 300, "height": 40 },
              "buttons": [
                { "id": "today_mode", "label": "📅 Today" },
                { "id": "upcoming_mode", "label": "⚡ Upcoming" },
                { "id": "all_mode", "label": "📋 All" }
              ]
            },
            {
              "id": "empty_state",
              "name": "Empty State",
              "type": "empty_state",
              "position": { "x": 400, "y": 100, "width": 640, "height": 300 },
              "content": "No tasks yet",
              "description": "📋 icon + heading + description + Add Task button"
            },
            {
              "id": "task_list",
              "name": "Task List",
              "type": "list",
              "position": { "x": 16, "y": 72, "width": 1408, "height": 468 },
              "description": "Scrollable list of task cards",
              "items": [
                {
                  "id": "task_card_1",
                  "name": "Task Card",
                  "type": "card",
                  "position": { "x": 0, "y": 0, "width": 1408, "height": 90 },
                  "children": [
                    {
                      "id": "status_icon",
                      "name": "Status Icon",
                      "position": { "x": 16, "y": 16, "width": 20, "height": 20 },
                      "content": "📝"
                    },
                    {
                      "id": "task_title",
                      "name": "Task Title",
                      "position": { "x": 48, "y": 12, "width": 800, "height": 24 },
                      "content": "Team Meeting Tomorrow 3PM"
                    },
                    {
                      "id": "priority_badge",
                      "name": "Priority Badge",
                      "position": { "x": 48, "y": 42, "width": 80, "height": 28 },
                      "bgColor": "linear-gradient(135deg, #DC2626, #EA580C)",
                      "content": "🔴 HIGH"
                    },
                    {
                      "id": "deadline_badge",
                      "name": "Deadline Badge",
                      "position": { "x": 142, "y": 42, "width": 100, "height": 28 },
                      "content": "📅 Apr 8"
                    },
                    {
                      "id": "score_box",
                      "name": "Priority Score",
                      "position": { "x": 1308, "y": 16, "width": 84, "height": 58 },
                      "bgColor": "linear-gradient(135deg, #EFF6FF, #CFFAFE)",
                      "content": "95\nScore"
                    },
                    {
                      "id": "action_buttons",
                      "name": "Action Buttons",
                      "position": { "x": 48, "y": 58, "width": 300, "height": 32 },
                      "children": [
                        {
                          "id": "done_btn",
                          "name": "Done Button",
                          "type": "button",
                          "position": { "x": 0, "y": 0, "width": 80, "height": 32 }
                        },
                        {
                          "id": "start_btn",
                          "name": "Start Button",
                          "type": "button",
                          "position": { "x": 90, "y": 0, "width": 80, "height": 32 }
                        },
                        {
                          "id": "delete_btn",
                          "name": "Delete Button",
                          "type": "button",
                          "position": { "x": 180, "y": 0, "width": 40, "height": 32 }
                        }
                      ]
                    }
                  ]
                }
              ]
            }
          ]
        }
      ]
    },
    {
      "id": "screen_command_palette",
      "name": "Command Palette Modal",
      "width": 800,
      "height": 600,
      "description": "Command palette overlay for quick task creation",
      "sections": [
        {
          "id": "modal_backdrop",
          "name": "Backdrop",
          "type": "backdrop",
          "opacity": 0.4,
          "blur": "blur-md"
        },
        {
          "id": "modal",
          "name": "Modal Container",
          "type": "card",
          "position": { "x": 64, "y": 80, "width": 672, "height": 440 },
          "borderRadius": 16,
          "shadow": "2xl",
          "children": [
            {
              "id": "input_section",
              "name": "Input Section",
              "type": "group",
              "position": { "x": 0, "y": 0, "width": 672, "height": 56 },
              "bgColor": "linear-gradient(to right, #FFFFFF, #F9FAFB)",
              "children": [
                {
                  "id": "search_icon",
                  "name": "Search Icon",
                  "position": { "x": 16, "y": 16, "width": 20, "height": 20 },
                  "content": "🔍"
                },
                {
                  "id": "input_field",
                  "name": "Input Field",
                  "type": "input",
                  "position": { "x": 44, "y": 12, "width": 550, "height": 32 },
                  "placeholder": "Type task or /command..."
                },
                {
                  "id": "close_btn",
                  "name": "Close Button",
                  "type": "button",
                  "position": { "x": 632, "y": 16, "width": 24, "height": 24 },
                  "content": "✕"
                }
              ]
            },
            {
              "id": "suggestions_list",
              "name": "Suggestions List",
              "type": "list",
              "position": { "x": 0, "y": 56, "width": 672, "height": 384 },
              "items": [
                {
                  "id": "suggestion_natural",
                  "name": "Natural Language Suggestion",
                  "type": "list_item",
                  "position": { "x": 0, "y": 0, "width": 672, "height": 48 },
                  "children": [
                    {
                      "id": "icon",
                      "type": "icon",
                      "position": { "x": 16, "y": 12, "width": 16, "height": 16 },
                      "content": "💡"
                    },
                    {
                      "id": "title",
                      "type": "text",
                      "position": { "x": 40, "y": 8, "width": 600, "height": 20 },
                      "content": "add meeting tomorrow 3pm high"
                    }
                  ]
                },
                {
                  "id": "suggestion_command",
                  "name": "Slash Command Suggestion",
                  "type": "list_item",
                  "position": { "x": 0, "y": 50, "width": 672, "height": 48 },
                  "children": [
                    {
                      "id": "icon",
                      "type": "icon",
                      "position": { "x": 16, "y": 12, "width": 16, "height": 16 },
                      "content": "⌘"
                    },
                    {
                      "id": "title",
                      "type": "text",
                      "position": { "x": 40, "y": 8, "width": 600, "height": 20 },
                      "content": "/add - Add new task"
                    }
                  ]
                }
              ]
            }
          ]
        }
      ]
    },
    {
      "id": "screen_mobile",
      "name": "Mobile View - 375px",
      "width": 375,
      "height": 812,
      "description": "Responsive mobile layout",
      "sections": [
        {
          "id": "header_mobile",
          "name": "Mobile Header",
          "type": "component",
          "position": { "x": 0, "y": 0, "width": 375, "height": 56 }
        },
        {
          "id": "calendar_mobile",
          "name": "Mobile Calendar",
          "type": "component",
          "position": { "x": 0, "y": 56, "width": 375, "height": 200 }
        },
        {
          "id": "tasks_mobile",
          "name": "Mobile Tasks",
          "type": "component",
          "position": { "x": 0, "y": 256, "width": 375, "height": 556 }
        }
      ]
    }
  ],
  "components": [
    {
      "id": "comp_header",
      "name": "Header",
      "description": "Main navigation bar component",
      "width": 1440,
      "height": 64,
      "properties": {
        "bgColor": "white",
        "darkBgColor": "gray-950",
        "borderBottom": "1px solid gray-200/50",
        "backdropFilter": "blur-xl"
      }
    },
    {
      "id": "comp_task_card",
      "name": "Task Card",
      "description": "Individual task display card",
      "width": 1408,
      "height": 90,
      "properties": {
        "bgColor": "white",
        "darkBgColor": "gray-900/50",
        "borderRadius": 12,
        "borderLeft": "4px",
        "shadow": "md"
      }
    },
    {
      "id": "comp_priority_badge",
      "name": "Priority Badge",
      "description": "Priority level indicator",
      "width": 80,
      "height": 28,
      "variants": [
        {
          "name": "High",
          "bgColor": "linear-gradient(135deg, #DC2626, #EA580C)",
          "textColor": "white"
        },
        {
          "name": "Medium",
          "bgColor": "linear-gradient(135deg, #EAB308, #EA580C)",
          "textColor": "white"
        },
        {
          "name": "Low",
          "bgColor": "linear-gradient(135deg, #16A34A, #10B981)",
          "textColor": "white"
        }
      ]
    },
    {
      "id": "comp_button",
      "name": "Button",
      "description": "Reusable button component",
      "variants": [
        {
          "name": "Primary",
          "bgColor": "linear-gradient(135deg, #3B82F6, #06B6D4)",
          "textColor": "white"
        },
        {
          "name": "Secondary",
          "bgColor": "gray-100",
          "textColor": "gray-900",
          "darkBgColor": "gray-800",
          "darkTextColor": "gray-50"
        },
        {
          "name": "Success",
          "bgColor": "linear-gradient(135deg, #16A34A, #10B981)",
          "textColor": "white"
        }
      ]
    }
  ],
  "colors": [
    {
      "id": "color_blue_600",
      "name": "Primary Blue",
      "value": "#3B82F6"
    },
    {
      "id": "color_cyan_600",
      "name": "Primary Cyan",
      "value": "#06B6D4"
    },
    {
      "id": "color_red_600",
      "name": "High Priority",
      "value": "#DC2626"
    },
    {
      "id": "color_yellow_600",
      "name": "Medium Priority",
      "value": "#EAB308"
    },
    {
      "id": "color_green_600",
      "name": "Low Priority",
      "value": "#16A34A"
    }
  ]
}
